autoemulate/__init__.py
autoemulate/calibration/__init__.py
autoemulate/calibration/base.py
autoemulate/calibration/bayes.py
autoemulate/calibration/history_matching.py
autoemulate/calibration/history_matching_dashboard.py
autoemulate/calibration/interval_excursion_set.py
autoemulate/callbacks/early_stopping.py
autoemulate/core/__init__.py
autoemulate/core/compare.py
autoemulate/core/device.py
autoemulate/core/logging_config.py
autoemulate/core/metrics.py
autoemulate/core/model_selection.py
autoemulate/core/plotting.py
autoemulate/core/reinitialize.py
autoemulate/core/results.py
autoemulate/core/save.py
autoemulate/core/sensitivity_analysis.py
autoemulate/core/tuner.py
autoemulate/core/types.py
autoemulate/data/utils.py
autoemulate/datasets/__init__.py
autoemulate/datasets/datasets.py
autoemulate/datasets/cardiac1/description.md
autoemulate/datasets/cardiac1/processed/outputs.csv
autoemulate/datasets/cardiac1/processed/parameters.csv
autoemulate/datasets/cardiac1/raw/outputs.csv
autoemulate/datasets/cardiac1/raw/parameters.csv
autoemulate/datasets/cardiac2/description.md
autoemulate/datasets/cardiac2/processed/outputs.csv
autoemulate/datasets/cardiac2/processed/parameters.csv
autoemulate/datasets/cardiac2/raw/outputs.csv
autoemulate/datasets/cardiac2/raw/parameters.csv
autoemulate/datasets/cardiac3/description.md
autoemulate/datasets/cardiac3/processed/outputs.csv
autoemulate/datasets/cardiac3/processed/parameters.csv
autoemulate/datasets/cardiac3/raw/outputs.csv
autoemulate/datasets/cardiac3/raw/parameters.csv
autoemulate/datasets/cardiac4/description.md
autoemulate/datasets/cardiac4/processed/outputs.csv
autoemulate/datasets/cardiac4/processed/parameters.csv
autoemulate/datasets/cardiac4/raw/outputs.csv
autoemulate/datasets/cardiac4/raw/parameters.csv
autoemulate/datasets/cardiac5/description.md
autoemulate/datasets/cardiac5/processed/outputs.csv
autoemulate/datasets/cardiac5/processed/parameters.csv
autoemulate/datasets/cardiac5/raw/passive_mechanics.tar.xz
autoemulate-2.0.0.dist-info/licenses/LICENSE
autoemulate-2.0.0.dist-info/METADATA
autoemulate-2.0.0.dist-info/WHEEL
autoemulate-2.0.0.dist-info/top_level.txt
autoemulate-2.0.0.dist-info/RECORD
