Metadata-Version: 2.4
Name: autoemulate
Version: 2.0.0
Summary: A python package for semi-automated emulation
Author: AutoEmulate contributors (see our GitHub page)
License-Expression: MIT
Project-URL: Homepage, https://alan-turing-institute.github.io/autoemulate/
Project-URL: Documentation, https://alan-turing-institute.github.io/autoemulate/
Project-URL: Repository, https://github.com/alan-turing-institute/autoemulate
Project-URL: Bug Tracker, https://github.com/alan-turing-institute/autoemulate/issues
Classifier: Development Status :: 5 - Production/Stable
Classifier: Intended Audience :: Science/Research
Classifier: Programming Language :: Python :: 3
Classifier: Programming Language :: Python :: 3.10
Classifier: Programming Language :: Python :: 3.11
Classifier: Programming Language :: Python :: 3.12
Classifier: Topic :: Scientific/Engineering
Requires-Python: <3.13,>=3.10
License-File: LICENSE
Requires-Dist: matplotlib>=3.7.2
Requires-Dist: seaborn>=0.12.2
Requires-Dist: scikit-learn<1.6.0,>=1.3.0
Requires-Dist: pandas>=2.1
Requires-Dist: torch>=2.1.0
Requires-Dist: scipy>=1.11.3
Requires-Dist: numpy>=1.24
Requires-Dist: joblib>=1.3.2
Requires-Dist: tqdm>=4.66.2
Requires-Dist: lightgbm>=4.3.0
Requires-Dist: ipywidgets>=8.1.2
Requires-Dist: gpytorch>=1.12
Requires-Dist: salib>=1.5.1
Requires-Dist: torcheval>=0.0.7
Requires-Dist: anytree>=2.12.1
Requires-Dist: torchmetrics>=1.7.1
Requires-Dist: pyro-ppl>=1.9.1
Requires-Dist: torchrbf>=0.0.1
Requires-Dist: arviz>=0.21.0
Requires-Dist: getdist>=1.7.2
Requires-Dist: einops>=0.8.1
Provides-Extra: docs
Requires-Dist: furo>=2023.9.10; extra == "docs"
Requires-Dist: sphinx-copybutton>=0.5.2; extra == "docs"
Requires-Dist: sphinx-autodoc-typehints>=1.24.0; extra == "docs"
Provides-Extra: dev
Requires-Dist: ipykernel>=6.25.0; extra == "dev"
Requires-Dist: pytest>=7.4.0; extra == "dev"
Requires-Dist: sphinx>=7.2.6; extra == "dev"
Requires-Dist: myst-parser>=2.0.0; extra == "dev"
Requires-Dist: furo>=2023.9.10; extra == "dev"
Requires-Dist: sphinx-copybutton>=0.5.2; extra == "dev"
Requires-Dist: sphinx-autodoc-typehints>=1.24.0; extra == "dev"
Requires-Dist: black>=23.10.1; extra == "dev"
Requires-Dist: pre-commit>=3.5.0; extra == "dev"
Requires-Dist: jupyter-book<2.0.0,>=1.0.0; extra == "dev"
Requires-Dist: pytest-cov>=4.1.0; extra == "dev"
Requires-Dist: coverage>=7.6.4; extra == "dev"
Requires-Dist: plotnine>=0.13.6; extra == "dev"
Requires-Dist: pyright==1.1.405; extra == "dev"
Requires-Dist: ruff==0.12.11; extra == "dev"
Provides-Extra: spatiotemporal
Requires-Dist: the-well>=1.1.0; extra == "spatiotemporal"
Requires-Dist: neuraloperator>=1.0.2; extra == "spatiotemporal"
Dynamic: license-file
